README.md
setup.py
debug_world_peeeng/__init__.py
debug_world_peeeng/print_str.py
debug_world_peeeng/test.py
debug_world_peeeng.egg-info/PKG-INFO
debug_world_peeeng.egg-info/SOURCES.txt
debug_world_peeeng.egg-info/dependency_links.txt
debug_world_peeeng.egg-info/top_level.txt