Metadata-Version: 2.1
Name: debug-world-peeeng
Version: 0.0.3
Summary: PyPI Tutorial
Home-page: https://github.com/
Author: Peeeng
Author-email: peeeng@qq.com
License: UNKNOWN
Platform: UNKNOWN
Classifier: Programming Language :: Python :: 3
Classifier: License :: OSI Approved :: MIT License
Classifier: Operating System :: OS Independent
Requires-Python: >=3
